tic/__init__.py
tic-0.2.0.dist-info/AUTHORS.md
tic-0.2.0.dist-info/LICENSE
tic-0.2.0.dist-info/METADATA
tic-0.2.0.dist-info/WHEEL
tic-0.2.0.dist-info/top_level.txt
tic-0.2.0.dist-info/RECORD
