Metadata-Version: 2.1
Name: tic
Version: 0.2.0
Summary: TIC is a library that acts as a Toolbox for Interpretability Comparison.
Home-page: https://github.com/tommartensen/tic
Author: Tom Martensen
Author-email: mail@tommartensen.de
License: MIT license
Keywords: tic
Platform: UNKNOWN
Classifier: Development Status :: 2 - Pre-Alpha
Classifier: Intended Audience :: Developers
Classifier: License :: OSI Approved :: MIT License
Classifier: Natural Language :: English
Classifier: Programming Language :: Python :: 3.6
Classifier: Programming Language :: Python :: 3.7
